<annotation>
    <folder>images</folder>
    <filename>DSC00502.JPG</filename>
    <size>
        <width>1920</width>
        <height>1920</height>
        <depth>3</depth>
    </size>
    <object>
        <name>c-3-f-s-r</name>
        <difficult>0</difficult>
        <bndbox>
            <xmin>1251.914185</xmin>
            <ymin>1087.726196</ymin>
            <xmax>1646.614136</xmax>
            <ymax>1451.942017</ymax>
        </bndbox>
    </object>
    <object>
        <name>c-2-f-o-r</name>
        <difficult>0</difficult>
        <bndbox>
            <xmin>919.295044</xmin>
            <ymin>1179.395386</ymin>
            <xmax>1305.622070</xmax>
            <ymax>1550.136108</ymax>
        </bndbox>
    </object>
    <object>
        <name>c-3-f-s-r</name>
        <difficult>0</difficult>
        <bndbox>
            <xmin>568.572144</xmin>
            <ymin>1219.930786</ymin>
            <xmax>933.749817</xmax>
            <ymax>1487.234863</ymax>
        </bndbox>
    </object>
    <object>
        <name>c-2-h-d-r</name>
        <difficult>0</difficult>
        <bndbox>
            <xmin>216.482056</xmin>
            <ymin>1218.318481</ymin>
            <xmax>593.945801</xmax>
            <ymax>1619.694336</ymax>
        </bndbox>
    </object>
    <object>
        <name>c-2-f-o-r</name>
        <difficult>0</difficult>
        <bndbox>
            <xmin>172.721832</xmin>
            <ymin>1008.371277</ymin>
            <xmax>551.986450</xmax>
            <ymax>1280.474731</ymax>
        </bndbox>
    </object>
    <object>
        <name>c-2-u-s-r</name>
        <difficult>0</difficult>
        <bndbox>
            <xmin>1222.363525</xmin>
            <ymin>769.769165</ymin>
            <xmax>1576.000000</xmax>
            <ymax>1120.388428</ymax>
        </bndbox>
    </object>
    <object>
        <name>c-1-h-s-r</name>
        <difficult>0</difficult>
        <bndbox>
            <xmin>1035.583496</xmin>
            <ymin>825.419434</ymin>
            <xmax>1312.571289</xmax>
            <ymax>1170.013428</ymax>
        </bndbox>
    </object>
    <object>
        <name>c-3-h-o-r</name>
        <difficult>0</difficult>
        <bndbox>
            <xmin>712.393433</xmin>
            <ymin>822.524658</ymin>
            <xmax>982.554565</xmax>
            <ymax>1168.495361</ymax>
        </bndbox>
    </object>
    <object>
        <name>c-2-f-o-r</name>
        <difficult>0</difficult>
        <bndbox>
            <xmin>418.442841</xmin>
            <ymin>814.312012</ymin>
            <xmax>786.854614</xmax>
            <ymax>1096.957153</ymax>
        </bndbox>
    </object>
    <object>
        <name>c-3-f-d-r</name>
        <difficult>0</difficult>
        <bndbox>
            <xmin>1455.779663</xmin>
            <ymin>611.747803</ymin>
            <xmax>1694.815430</xmax>
            <ymax>919.596802</ymax>
        </bndbox>
    </object>
    <object>
        <name>c-1-h-s-r</name>
        <difficult>0</difficult>
        <bndbox>
            <xmin>909.988586</xmin>
            <ymin>577.265747</ymin>
            <xmax>1203.731689</xmax>
            <ymax>905.886963</ymax>
        </bndbox>
    </object>
    <object>
        <name>c-1-u-o-r</name>
        <difficult>0</difficult>
        <bndbox>
            <xmin>377.445343</xmin>
            <ymin>596.746155</ymin>
            <xmax>604.798584</xmax>
            <ymax>894.722961</ymax>
        </bndbox>
    </object>
    <object>
        <name>c-2-u-o-r</name>
        <difficult>0</difficult>
        <bndbox>
            <xmin>49.927334</xmin>
            <ymin>576.605652</ymin>
            <xmax>410.965637</xmax>
            <ymax>873.535889</ymax>
        </bndbox>
    </object>
    <object>
        <name>c-3-f-d-r</name>
        <difficult>0</difficult>
        <bndbox>
            <xmin>1294.807007</xmin>
            <ymin>292.517944</ymin>
            <xmax>1584.985962</xmax>
            <ymax>604.779724</ymax>
        </bndbox>
    </object>
    <object>
        <name>c-3-u-d-r</name>
        <difficult>0</difficult>
        <bndbox>
            <xmin>1059.024170</xmin>
            <ymin>374.409241</ymin>
            <xmax>1403.146606</xmax>
            <ymax>666.851135</ymax>
        </bndbox>
    </object>
    <object>
        <name>c-2-u-o-r</name>
        <difficult>0</difficult>
        <bndbox>
            <xmin>660.656250</xmin>
            <ymin>419.517792</ymin>
            <xmax>941.651367</xmax>
            <ymax>724.179749</ymax>
        </bndbox>
    </object>
    <object>
        <name>c-1-h-o-r</name>
        <difficult>0</difficult>
        <bndbox>
            <xmin>499.542114</xmin>
            <ymin>349.195923</ymin>
            <xmax>738.172485</xmax>
            <ymax>629.587524</ymax>
        </bndbox>
    </object>
    <object>
        <name>c-2-h-o-r</name>
        <difficult>0</difficult>
        <bndbox>
            <xmin>295.280609</xmin>
            <ymin>266.616272</ymin>
            <xmax>624.684448</xmax>
            <ymax>546.677856</ymax>
        </bndbox>
    </object>
    <object>
        <name>c-2-u-d-r</name>
        <difficult>0</difficult>
        <bndbox>
            <xmin>852.301697</xmin>
            <ymin>184.451569</ymin>
            <xmax>1078.645996</xmax>
            <ymax>456.668152</ymax>
        </bndbox>
    </object>
    <object>
        <name>c-3-u-d-r</name>
        <difficult>0</difficult>
        <bndbox>
            <xmin>1137.634155</xmin>
            <ymin>129.772537</ymin>
            <xmax>1400.110596</xmax>
            <ymax>416.641907</ymax>
        </bndbox>
    </object>
</annotation>