<annotation>
    <folder>images</folder>
    <filename>DSC00486.JPG</filename>
    <size>
        <width>1920</width>
        <height>1920</height>
        <depth>3</depth>
    </size>
    <object>
        <name>c-2-h-o-g</name>
        <difficult>0</difficult>
        <bndbox>
            <xmin>1340.019287</xmin>
            <ymin>1306.404663</ymin>
            <xmax>1754.180786</xmax>
            <ymax>1578.413818</ymax>
        </bndbox>
    </object>
    <object>
        <name>c-1-f-d-g</name>
        <difficult>0</difficult>
        <bndbox>
            <xmin>485.021332</xmin>
            <ymin>1388.654297</ymin>
            <xmax>935.013306</xmax>
            <ymax>1757.603516</ymax>
        </bndbox>
    </object>
    <object>
        <name>c-1-h-d-r</name>
        <difficult>0</difficult>
        <bndbox>
            <xmin>902.605591</xmin>
            <ymin>1222.240967</ymin>
            <xmax>1337.369629</xmax>
            <ymax>1501.934814</ymax>
        </bndbox>
    </object>
    <object>
        <name>c-3-u-d-p</name>
        <difficult>0</difficult>
        <bndbox>
            <xmin>199.962357</xmin>
            <ymin>1207.201660</ymin>
            <xmax>634.452942</xmax>
            <ymax>1525.912964</ymax>
        </bndbox>
    </object>
    <object>
        <name>c-3-u-d-p</name>
        <difficult>0</difficult>
        <bndbox>
            <xmin>583.998047</xmin>
            <ymin>955.955200</ymin>
            <xmax>999.969971</xmax>
            <ymax>1280.455933</ymax>
        </bndbox>
    </object>
    <object>
        <name>c-1-h-d-r</name>
        <difficult>0</difficult>
        <bndbox>
            <xmin>226.759720</xmin>
            <ymin>905.415466</ymin>
            <xmax>643.099365</xmax>
            <ymax>1237.714111</ymax>
        </bndbox>
    </object>
    <object>
        <name>c-1-f-o-p</name>
        <difficult>0</difficult>
        <bndbox>
            <xmin>1492.666016</xmin>
            <ymin>862.513306</ymin>
            <xmax>1913.871094</xmax>
            <ymax>1196.886230</ymax>
        </bndbox>
    </object>
    <object>
        <name>c-2-u-d-g</name>
        <difficult>0</difficult>
        <bndbox>
            <xmin>1261.154541</xmin>
            <ymin>757.143738</ymin>
            <xmax>1511.212891</xmax>
            <ymax>1070.584106</ymax>
        </bndbox>
    </object>
    <object>
        <name>c-2-u-o-r</name>
        <difficult>0</difficult>
        <bndbox>
            <xmin>997.773010</xmin>
            <ymin>769.986023</ymin>
            <xmax>1289.253174</xmax>
            <ymax>1104.443848</ymax>
        </bndbox>
    </object>
    <object>
        <name>c-2-h-o-r</name>
        <difficult>0</difficult>
        <bndbox>
            <xmin>611.398926</xmin>
            <ymin>752.778015</ymin>
            <xmax>1001.591858</xmax>
            <ymax>1050.962280</ymax>
        </bndbox>
    </object>
    <object>
        <name>c-1-h-d-p</name>
        <difficult>0</difficult>
        <bndbox>
            <xmin>178.945007</xmin>
            <ymin>753.089172</ymin>
            <xmax>558.313354</xmax>
            <ymax>1009.465088</ymax>
        </bndbox>
    </object>
    <object>
        <name>c-2-u-o-g</name>
        <difficult>0</difficult>
        <bndbox>
            <xmin>1355.831665</xmin>
            <ymin>479.656281</ymin>
            <xmax>1690.562988</xmax>
            <ymax>659.996277</ymax>
        </bndbox>
    </object>
    <object>
        <name>c-3-u-d-r</name>
        <difficult>0</difficult>
        <bndbox>
            <xmin>1047.539551</xmin>
            <ymin>533.967529</ymin>
            <xmax>1394.575684</xmax>
            <ymax>761.773376</ymax>
        </bndbox>
    </object>
    <object>
        <name>c-3-f-o-g</name>
        <difficult>0</difficult>
        <bndbox>
            <xmin>875.072815</xmin>
            <ymin>455.178406</ymin>
            <xmax>1221.580933</xmax>
            <ymax>703.143555</ymax>
        </bndbox>
    </object>
    <object>
        <name>c-3-h-o-g</name>
        <difficult>0</difficult>
        <bndbox>
            <xmin>533.448975</xmin>
            <ymin>482.220947</ymin>
            <xmax>880.051392</xmax>
            <ymax>767.449585</ymax>
        </bndbox>
    </object>
    <object>
        <name>c-1-u-o-r</name>
        <difficult>0</difficult>
        <bndbox>
            <xmin>170.986893</xmin>
            <ymin>564.677979</ymin>
            <xmax>505.699280</xmax>
            <ymax>776.228027</ymax>
        </bndbox>
    </object>
    <object>
        <name>c-3-u-s-r</name>
        <difficult>0</difficult>
        <bndbox>
            <xmin>1199.941284</xmin>
            <ymin>231.681717</ymin>
            <xmax>1424.607178</xmax>
            <ymax>450.907104</ymax>
        </bndbox>
    </object>
    <object>
        <name>c-1-h-d-g</name>
        <difficult>0</difficult>
        <bndbox>
            <xmin>773.936829</xmin>
            <ymin>255.188339</ymin>
            <xmax>1072.375732</xmax>
            <ymax>513.289673</ymax>
        </bndbox>
    </object>
    <object>
        <name>c-2-u-d-r</name>
        <difficult>0</difficult>
        <bndbox>
            <xmin>506.481903</xmin>
            <ymin>260.874023</ymin>
            <xmax>785.723145</xmax>
            <ymax>513.978027</ymax>
        </bndbox>
    </object>
    <object>
        <name>c-2-u-d-r</name>
        <difficult>0</difficult>
        <bndbox>
            <xmin>204.045135</xmin>
            <ymin>318.862701</ymin>
            <xmax>527.989502</xmax>
            <ymax>569.043579</ymax>
        </bndbox>
    </object>
</annotation>